argparse_subargs/__init__.py
argparse_subargs/__version__.py
argparse_subargs/py.typed
argparse_subargs-0.9.2.dist-info/METADATA
argparse_subargs-0.9.2.dist-info/WHEEL
argparse_subargs-0.9.2.dist-info/licenses/LICENSE
argparse_subargs-0.9.2.dist-info/RECORD
