Metadata-Version: 2.3
Name: argparse_subargs
Version: 0.9.2
Summary: Parse parameter lists in argparse arguments, e.g. --arg sub1 sub2=val ...
Project-URL: Homepage, https://github.com/v-r-b/argparse_subargs
Project-URL: Issues, https://github.com/v-r-b/argparse_subargs/issues
Author-email: volker <volker@vrbdev.eu>
Maintainer-email: volker <volker@vrbdev.eu>
License-File: LICENSE
Classifier: Development Status :: 4 - Beta
Classifier: Intended Audience :: Developers
Classifier: License :: OSI Approved :: GNU General Public License v3 (GPLv3)
Classifier: Operating System :: OS Independent
Classifier: Programming Language :: Python :: 3
Classifier: Topic :: Software Development :: Libraries :: Python Modules
Requires-Python: >=3.9
